{
  "Timestamp": "2026-03-14T15:26:01.2120341-07:00",
  "Experiment": 8,
  "CsvPath": "C:\\Projects\\Hone\\sample-api\\results\\experiment-8\\dotnet-counters.csv",
  "TotalSamples": 17672,
  "Runtime": {
    "CpuUsage": {
      "Avg": 18.0,
      "Min": 0.0,
      "Max": 29.0,
      "Last": 20.0,
      "Samples": 610
    },
    "WorkingSetMB": {
      "Avg": 943.17,
      "Min": 317.0,
      "Max": 1963.0,
      "Last": 1828.0,
      "Samples": 610
    },
    "GcHeapSizeMB": {
      "Avg": 340.86,
      "Min": 9.0,
      "Max": 1662.0,
      "Last": 313.0,
      "Samples": 610
    },
    "Gen0Collections": {
      "Avg": 9871874.61,
      "Min": 0.0,
      "Max": 209184424.0,
      "Last": 1.0,
      "Samples": 1219
    },
    "Gen1Collections": {
      "Avg": 14181039.74,
      "Min": 0.0,
      "Max": 99849368.0,
      "Last": 0.0,
      "Samples": 1219
    },
    "Gen2Collections": {
      "Avg": 13513069.92,
      "Min": 0.0,
      "Max": 33269072.0,
      "Last": 0.0,
      "Samples": 1219
    },
    "Gen0SizeMB": {
      "Avg": 19759957.16,
      "Min": 384.0,
      "Max": 209184424.0,
      "Last": 5847296.0,
      "Samples": 609
    },
    "Gen1SizeMB": {
      "Avg": 28385364.26,
      "Min": 384.0,
      "Max": 99849368.0,
      "Last": 28613296.0,
      "Samples": 609
    },
    "Gen2SizeMB": {
      "Avg": 27048328.76,
      "Min": 8708216.0,
      "Max": 33269072.0,
      "Last": 33269072.0,
      "Samples": 609
    },
    "LOHSizeMB": {
      "Avg": 390464.0,
      "Min": 390464.0,
      "Max": 390464.0,
      "Last": 390464.0,
      "Samples": 609
    },
    "POHSizeMB": {
      "Avg": 2045948.52,
      "Min": 641944.0,
      "Max": 2165536.0,
      "Last": 2165536.0,
      "Samples": 609
    },
    "GcPauseRatio": {
      "Avg": 4.41,
      "Min": 0.0,
      "Max": 75.0,
      "Last": 0.0,
      "Samples": 609
    },
    "AllocRateMB": {
      "Avg": 582160679.49,
      "Min": 0.0,
      "Max": 791758520.0,
      "Last": 566173016.0,
      "Samples": 610
    },
    "ExceptionCount": {
      "Avg": 397.61,
      "Min": 0.0,
      "Max": 1942.0,
      "Last": 614.0,
      "Samples": 609
    },
    "ThreadPoolThreads": {
      "Avg": 26.47,
      "Min": 23.0,
      "Max": 40.0,
      "Last": 32.0,
      "Samples": 610
    },
    "ThreadPoolQueue": {
      "Avg": 81.79,
      "Min": 0.0,
      "Max": 149.0,
      "Last": 120.0,
      "Samples": 610
    },
    "ThreadPoolCompleted": {
      "Avg": 29956.23,
      "Min": 0.0,
      "Max": 42799.0,
      "Last": 29701.0,
      "Samples": 610
    },
    "MonitorContentions": {
      "Avg": 7.25,
      "Min": 0.0,
      "Max": 130.0,
      "Last": 22.0,
      "Samples": 610
    },
    "ActiveTimers": {
      "Avg": 3.74,
      "Min": 2.0,
      "Max": 12.0,
      "Last": 2.0,
      "Samples": 609
    },
    "Assemblies": {
      "Avg": 159.0,
      "Min": 159.0,
      "Max": 159.0,
      "Last": 159.0,
      "Samples": 609
    }
  },
  "AspNetCore": {
    "RequestRate": {
      "Avg": 1167.11,
      "Min": 0.0,
      "Max": 1596.0,
      "Last": 1337.0,
      "Samples": 609
    },
    "TotalRequests": {
      "Avg": 356671.59,
      "Min": 0.0,
      "Max": 710773.0,
      "Last": 710773.0,
      "Samples": 609
    },
    "CurrentRequests": {
      "Avg": 159.6,
      "Min": 0.0,
      "Max": 449.0,
      "Last": 291.0,
      "Samples": 609
    },
    "FailedRequests": {
      "Avg": 0.0,
      "Min": 0.0,
      "Max": 0.0,
      "Last": 0.0,
      "Samples": 609
    }
  },
  "HttpConnections": {
    "CurrentConnections": null,
    "TotalConnections": null
  },
  "HttpClient": {
    "CurrentRequests": null,
    "RequestsStarted": null,
    "RequestsFailed": null
  }
}
